search_addr/__init__.py
address_search_google-0.0.1.dist-info/LICENSE
address_search_google-0.0.1.dist-info/METADATA
address_search_google-0.0.1.dist-info/WHEEL
address_search_google-0.0.1.dist-info/top_level.txt
address_search_google-0.0.1.dist-info/RECORD
