Metadata-Version: 2.1
Name: address-search-google
Version: 0.0.1
Summary: Google Search API with Caching for repeated search.
Home-page: https://github.com/dextrop/address_search_google
Author: Saurabh Pandey
Author-email: scoder91@gmail.com
License: UNKNOWN
Platform: UNKNOWN
Classifier: Programming Language :: Python :: 3
Classifier: Operating System :: OS Independent
Requires-Python: >=3.6
